HoseinTabr/An_Wb.py
HoseinTabr/Cliob.py
HoseinTabr/HoseinTabr.py
HoseinTabr/__init__.py
HoseinTabr/encryption.py
hoseinTabr-2.0.0.dist-info/LICENSE
hoseinTabr-2.0.0.dist-info/METADATA
hoseinTabr-2.0.0.dist-info/WHEEL
hoseinTabr-2.0.0.dist-info/top_level.txt
hoseinTabr-2.0.0.dist-info/RECORD
