Metadata-Version: 2.1
Name: hoseinTabr
Version: 2.0.0
Summary: im hosein
Home-page: https://github.com/pypa/sampleproject
Classifier: Programming Language :: Python :: 3
Classifier: License :: OSI Approved :: MIT License
Classifier: Operating System :: OS Independent
License-File: LICENSE
